{
    "id": "feitgeregistreerdevoorziening",
    "title": "Feitgeregistreerdevoorziening",
    "description": "Beschrijving voor feitgeregistreerdevoorziening",
    "shortname": "feitGrgVrzng",
    "type": "table",
    "version": "0.0.1",
    "status": "stable",
    "schema": {
        "$schema": "http://json-schema.org/draft-07/schema#",
        "type": "object",
        "additionalProperties": false,
        "identifier": [
            "xcasusnr",
            "xclientnr",
            "xvoorzieningnr"
        ],
        "required": [
            "schema",
            "xcasusnr",
            "xclientnr",
            "xvoorzieningnr"            
        ],
        "display": "xcasusnr",
        "properties": {
            "schema": {
                "$ref": "https://schemas.data.amsterdam.nl/schema@v4.0.0#/definitions/schema"
            },
            "rbeschikt": {
                "type": "number",
                "title": "Rbeschikt",
                "description": "Beschrijving voor RBESCHIKT"
            },
            "rleeftijd": {
                "type": "number",
                "title": "Rleeftijd",
                "description": "Beschrijving voor RLEEFTIJD"
            },
            "rleeftijdopingangsdatum": {
                "type": "number",
                "title": "Rleeftijdopingangsdatum",
                "description": "Beschrijving voor RLEEFTIJDOPINGANGSDATUM"
            },
            "rleverancier": {
                "type": "string",
                "title": "Rleverancier",
                "description": "Beschrijving voor RLEVERANCIER"
            },
            "rregeling": {
                "type": "number",
                "title": "Rregeling",
                "description": "Beschrijving voor RREGELING"
            },
            "maantal": {
                "type": "number",
                "title": "Maantal",
                "description": "Beschrijving voor MAANTAL"
            },
            "rcheckdatum": {
                "type": "number",
                "title": "Rcheckdatum",
                "description": "Beschrijving voor RCHECKDATUM"
            },
            "reinddatum": {
                "type": "number",
                "title": "Reinddatum",
                "description": "Beschrijving voor REINDDATUM"
            },
            "reindegeldigvorigezelfdevrz": {
                "type": "number",
                "title": "Reindegeldigvorigezelfdevrz",
                "description": "Beschrijving voor REINDEGELDIGVORIGEZELFDEVRZ"
            },
            "rgemeente": {
                "type": "string",
                "title": "Rgemeente",
                "description": "Beschrijving voor RGEMEENTE"
            },
            "ringangsdatumvoorziening": {
                "type": "number",
                "title": "Ringangsdatumvoorziening",
                "description": "Beschrijving voor RINGANGSDATUMVOORZIENING"
            },
            "rvoorziening": {
                "type": "string",
                "title": "Rvoorziening",
                "description": "Beschrijving voor RVOORZIENING"
            },
            "rgeslacht": {
                "type": "string",
                "title": "Rgeslacht",
                "description": "Beschrijving voor RGESLACHT"
            },
            "xcasusnr": {
                "type": "string",
                "title": "Xcasusnr",
                "description": "Beschrijving voor XCASUSNR"
            },
            "xclientnr": {
                "type": "string",
                "title": "Xclientnr",
                "description": "Beschrijving voor XCLIENTNR"
            },
            "xvoorzieningnr": {
                "type": "string",
                "title": "Xvoorzieningnr",
                "description": "Beschrijving voor XVOORZIENINGNR"
            },
            "rleverancierlevering": {
                "type": "string",
                "title": "Rleverancierlevering",
                "description": "Beschrijving voor RLEVERANCIERLEVERING"
            },
            "mtaLaadDatumtijd": {
                "type": "string",
                "format": "date-time",
                "title": "Mta laad datumtijd",
                "description": "Beschrijving voor MTA_LAAD_DATUMTIJD"
            }
        }
    }
}