{
  "id": "overlastgebieden",
  "type": "dataset",
  "auth": "OPENBAAR",
  "authorizationGrantor": "n.v.t.",
  "theme": [
    "openbare orde en veiligheid"
  ],
  "homepage": "https://data.amsterdam.nl",
  "owner": "Gemeente Amsterdam, Openbare Orde en Veiligheid Amsterdam",
  "dateModified": "2022-02-23T00:00:00+01:00",
  "spatialDescription": "Gemeente Amsterdam",
  "default_version": "1.0.1",
  "title": "Overlastgebieden gemeente Amsterdam",
  "language": "nl",
  "dateCreated": "2020-02-09T00:00:00+01:00",
  "license": "Creative Commons, Naamsvermelding",
  "hasBeginning": "2020-02-09T00:00:00+01:00",
  "accrualPeriodicity": "dagelijks",
  "creator": "bronhouder onbekend",
  "publisher": {
    "$ref": "publishers/SVD"
  },
  "description": "Overlastgebieden Amsterdam.",
  "keywords": [
    "openbare orde en veiligheid",
    "overlastgebieden",
    "sluitingstijden kernwallen",
    "cameratoezicht",
    "overlast",
    "dealeroverlast",
    "verboden",
    "verbod",
    "alcohol",
    "alcoholverkoop",
    "barbecue",
    "groepsfiets",
    "messen",
    "rondleiding",
    "straatartiest",
    "blowen"
  ],
  "crs": "EPSG:28992",
  "objective": "Publiceren van de locaties voor verboden activiteiten of gedragingen in de openbare ruimte.",
  "defaultVersion": "v1",
  "versions": {
    "v1": {
      "status": "beschikbaar",
      "lifecycleStatus": "stable",
      "version": "1.0.1",
      "tables": [
        {
          "id": "alcoholverkoopverbod",
          "$ref": "alcoholverkoopverbod/v2"
        },
        {
          "id": "sluitingstijdenkernwallen",
          "$ref": "sluitingstijdenkernwallen/v2"
        },
        {
          "id": "alcoholverbod",
          "$ref": "alcoholverbod/v2"
        },
        {
          "id": "algemeenoverlast",
          "$ref": "algemeenoverlast/v2"
        },
        {
          "id": "barbecueverbod",
          "$ref": "barbecueverbod/v2"
        },
        {
          "id": "cameratoezicht",
          "$ref": "cameratoezicht/v2"
        },
        {
          "id": "dealeroverlast",
          "$ref": "dealeroverlast/v2"
        },
        {
          "id": "groepsfietsverbod",
          "$ref": "groepsfietsverbod/v2"
        },
        {
          "id": "messenverbod",
          "$ref": "messenverbod/v2"
        },
        {
          "id": "rondleidingverbod",
          "$ref": "rondleidingverbod/v2"
        },
        {
          "id": "straatartiestverbod",
          "$ref": "straatartiestverbod/v2"
        },
        {
          "id": "taxistandplaats",
          "$ref": "taxistandplaats/v1"
        },
        {
          "id": "uitgaansoverlast",
          "$ref": "uitgaansoverlast/v1"
        },
        {
          "id": "vuurwerkvrij",
          "$ref": "vuurwerkvrij/v1"
        },
        {
          "id": "blowverbodsgebied",
          "$ref": "blowverbodsgebied/v2"
        }
      ]
    }
  }
}
